tpip/__init__.py
tpip/mirrors.py
tpip/tpip.py
tpip-0.2.0.dist-info/METADATA
tpip-0.2.0.dist-info/WHEEL
tpip-0.2.0.dist-info/entry_points.txt
tpip-0.2.0.dist-info/top_level.txt
tpip-0.2.0.dist-info/RECORD
