Metadata-Version: 2.2
Name: tpip
Version: 0.2.0
Summary: 优选 pip 镜像源，提升下载速度的命令行工具。
Author-email: yjys <wsy52552@gmail.com>
Project-URL: Homepage, https://github.com/wsy-yjys/tpip
Project-URL: Issues, https://github.com/wsy-yjys/tpip/issues
Keywords: pip,mirror,Chinese,speed,cli
Classifier: License :: OSI Approved :: MIT License
Classifier: Intended Audience :: Developers
Classifier: Operating System :: OS Independent
Classifier: Programming Language :: Python :: 3
Classifier: Programming Language :: Python :: 3.6
Classifier: Programming Language :: Python :: 3.7
Classifier: Programming Language :: Python :: 3.8
Classifier: Programming Language :: Python :: 3.9
Classifier: Programming Language :: Python :: 3.10
Classifier: Programming Language :: Python :: 3.11
Classifier: Topic :: Software Development :: Libraries :: Python Modules
Classifier: Topic :: System :: Installation/Setup
Classifier: Topic :: Utilities
Requires-Python: >=3.7
Requires-Dist: requests
Requires-Dist: aiohttp
Requires-Dist: prettytable
